statsman/__init__.py
statsman/__main__.py
statsman/cli.py
statsman/system_monitor.py
statsman/ui/__init__.py
statsman/ui/app.py
statsman/ui/renderer.py
statsman/ui/components/__init__.py
statsman/ui/components/cpu_cores.py
statsman/ui/components/header_footer.py
statsman/ui/components/memory_display.py
statsman/ui/components/network_display.py
statsman/ui/components/process_list.py
statsman/ui/components/system_overview.py
statsman/ui/layouts/__init__.py
statsman/ui/layouts/content_size_fitter.py
statsman/ui/layouts/drawing_primitives.py
statsman/ui/layouts/grid_layout.py
statsman/ui/layouts/horizontal_layout.py
statsman/ui/layouts/layout_element.py
statsman/ui/layouts/layout_manager.py
statsman/ui/layouts/terminal_controller.py
statsman/ui/layouts/vertical_layout.py
statsman-0.1.3.dist-info/licenses/LICENSE
statsman-0.1.3.dist-info/METADATA
statsman-0.1.3.dist-info/WHEEL
statsman-0.1.3.dist-info/entry_points.txt
statsman-0.1.3.dist-info/top_level.txt
statsman-0.1.3.dist-info/RECORD
