Metadata-Version: 2.4
Name: statsman
Version: 0.1.3
Summary: A terminal-based system monitoring tool with manual UI rendering, full-screen support, and dynamic layout management
Author-email: Exil Productions <exil.productions.business@gmail.com>
License: MIT
Project-URL: Homepage, https://exil.dev
Project-URL: Repository, https://github.com/ExilProductions/statsman
Project-URL: Issues, https://github.com/ExilProductions/statsman/issues
Classifier: Development Status :: 4 - Beta
Classifier: Environment :: Console
Classifier: Intended Audience :: System Administrators
Classifier: License :: OSI Approved :: MIT License
Classifier: Operating System :: POSIX :: Linux
Classifier: Programming Language :: Python :: 3
Classifier: Programming Language :: Python :: 3.8
Classifier: Programming Language :: Python :: 3.9
Classifier: Programming Language :: Python :: 3.10
Classifier: Programming Language :: Python :: 3.11
Classifier: Programming Language :: Python :: 3.12
Classifier: Topic :: System :: Monitoring
Classifier: Topic :: System :: Systems Administration
Requires-Python: >=3.8
License-File: LICENSE
Requires-Dist: psutil>=5.9.0
Requires-Dist: click>=8.0.0
Provides-Extra: dev
Requires-Dist: black>=23.0.0; extra == "dev"
Requires-Dist: flake8>=6.0.0; extra == "dev"
Requires-Dist: mypy>=1.0.0; extra == "dev"
Dynamic: license-file
